{
  "main": {
    "id": "cddc458a52dfc4c2",
    "type": "split",
    "children": [
      {
        "id": "7e6b492b79c0e433",
        "type": "tabs",
        "dimension": 72.46631517281781,
        "children": [
          {
            "id": "7f63f405cc55c1a0",
            "type": "leaf",
            "state": {
              "type": "markdown",
              "state": {
                "file": "» Notes/Atomic/Project Cost Management.md",
                "mode": "source",
                "backlinks": true,
                "source": false
              }
            }
          }
        ]
      },
      {
        "id": "e89c2ee62d00449b",
        "type": "tabs",
        "dimension": 27.533684827182192,
        "children": [
          {
            "id": "b0d201fb14d68b6d",
            "type": "leaf",
            "state": {
              "type": "localgraph",
              "state": {
                "file": "» Notes/Atomic/Project Cost Management.md",
                "options": {
                  "collapse-filter": true,
                  "search": "",
                  "localJumps": 2,
                  "localBacklinks": true,
                  "localForelinks": true,
                  "localInterlinks": false,
                  "showTags": false,
                  "showAttachments": false,
                  "hideUnresolved": false,
                  "collapse-color-groups": true,
                  "colorGroups": [],
                  "collapse-display": false,
                  "showArrow": true,
                  "textFadeMultiplier": 0,
                  "nodeSizeMultiplier": 1,
                  "lineSizeMultiplier": 1,
                  "collapse-forces": true,
                  "centerStrength": 0.518713248970312,
                  "repelStrength": 10,
                  "linkStrength": 1,
                  "linkDistance": 250,
                  "scale": 0.9065480705764472,
                  "close": true
                }
              }
            }
          },
          {
            "id": "14103f26cad56a3c",
            "type": "leaf",
            "state": {
              "type": "graph",
              "state": {}
            }
          }
        ]
      }
    ],
    "direction": "vertical"
  },
  "left": {
    "id": "a9db8479e8229784",
    "type": "split",
    "children": [
      {
        "id": "df71673bef8e97da",
        "type": "tabs",
        "children": [
          {
            "id": "cef6f232d564ca5a",
            "type": "leaf",
            "state": {
              "type": "file-explorer",
              "state": {
                "sortOrder": "alphabetical"
              }
            }
          },
          {
            "id": "341442d45d6b5e71",
            "type": "leaf",
            "state": {
              "type": "search",
              "state": {
                "query": "tag:#分詞器",
                "matchingCase": true,
                "explainSearch": false,
                "collapseAll": true,
                "extraContext": false,
                "sortOrder": "alphabetical"
              }
            }
          },
          {
            "id": "1bc11ef43887bc23",
            "type": "leaf",
            "state": {
              "type": "starred",
              "state": {}
            }
          },
          {
            "id": "3cdc0fa36b8d9777",
            "type": "leaf",
            "state": {
              "type": "bookmarks",
              "state": {}
            }
          },
          {
            "id": "d5e1e2be15a68b5c",
            "type": "leaf",
            "state": {
              "type": "file-tree-view",
              "state": {}
            }
          }
        ],
        "currentTab": 4
      }
    ],
    "direction": "horizontal",
    "width": 282.51103591918945,
    "collapsed": true
  },
  "right": {
    "id": "68e330dec2c08a37",
    "type": "split",
    "children": [
      {
        "id": "add047b1118d202a",
        "type": "tabs",
        "children": [
          {
            "id": "17eb92a6239b54df",
            "type": "leaf",
            "state": {
              "type": "backlink",
              "state": {
                "file": "» Notes/Atomic/Project Cost Management.md",
                "collapseAll": false,
                "extraContext": false,
                "sortOrder": "alphabetical",
                "showSearch": false,
                "searchQuery": "",
                "backlinkCollapsed": false,
                "unlinkedCollapsed": false
              }
            }
          },
          {
            "id": "233dbe7a27ca4243",
            "type": "leaf",
            "state": {
              "type": "outgoing-link",
              "state": {
                "file": "» Notes/Atomic/Project Cost Management.md",
                "linksCollapsed": false,
                "unlinkedCollapsed": false
              }
            }
          },
          {
            "id": "0c87cba199260fb0",
            "type": "leaf",
            "state": {
              "type": "advanced-tables-toolbar",
              "state": {}
            }
          },
          {
            "id": "21a4c9d080ba0b6d",
            "type": "leaf",
            "state": {
              "type": "tag",
              "state": {
                "sortOrder": "frequency",
                "useHierarchy": true
              }
            }
          },
          {
            "id": "9425de3f6185bf10",
            "type": "leaf",
            "state": {
              "type": "outline",
              "state": {
                "file": "» Notes/Atomic/Project Cost Management.md"
              }
            }
          },
          {
            "id": "f8655c264c18d2d1",
            "type": "leaf",
            "state": {
              "type": "calendar",
              "state": {}
            }
          },
          {
            "id": "b351daec9efe29d0",
            "type": "leaf",
            "state": {
              "type": "FANTASY_CALENDAR",
              "state": {}
            }
          },
          {
            "id": "135277ee9e447b16",
            "type": "leaf",
            "state": {
              "type": "all-properties",
              "state": {
                "sortOrder": "frequency"
              }
            }
          },
          {
            "id": "574aea05d4ffaa4e",
            "type": "leaf",
            "state": {
              "type": "file-properties",
              "state": {
                "file": "» Notes/Atomic/Project Cost Management.md"
              }
            }
          }
        ],
        "currentTab": 8
      }
    ],
    "direction": "horizontal",
    "width": 300,
    "collapsed": true
  },
  "left-ribbon": {
    "hiddenItems": {
      "switcher:Open quick switcher": false,
      "graph:Open graph view": false,
      "daily-notes:Open today's daily note": false,
      "obsidian-excalidraw-plugin:Create new drawing": false,
      "canvas:Create new canvas": false,
      "command-palette:Open command palette": false,
      "notion-like-tables:Create Notion-Like table": false,
      "table-editor-obsidian:Advanced Tables Toolbar": false,
      "file-tree-alternative:File Tree Alternative Plugin": false,
      "workspaces:Manage workspace layouts": false,
      "fantasy-calendar:Open Large Fantasy Calendar": false,
      "templater-obsidian:Templater": false,
      "templates:Insert template": false
    }
  },
  "active": "7f63f405cc55c1a0",
  "lastOpenFiles": [
    "» Notes/Atomic/Project Management — Constraints.md",
    "» Notes/Atomic/Cost.md",
    "» Notes/Atomic/Project Cost Management.md",
    "» Notes/__temporary/Project Management.md",
    "Plugins/Notion/window manager checklist.table",
    "» Notes/__temporary/Untitled 2.md",
    "» Notes/✦ Papers.md",
    "» Notes/__temporary/Project Schedule Management.md",
    "Plugins/Daily Notes/2023-11-29.md",
    "» Notes/Atomic/Capture The Flag.md",
    "Plugins/Daily Notes/2023-11-28.md",
    "» Notes/Atomic/Discrete Probability Distribution.md",
    "README.md",
    "Plugins/Daily Notes/2023-11-22.md",
    "Plugins/Daily Notes/2023-11-21.md",
    "» Notes/Atomic/(root-me.org) Encoding - UU.md",
    "Plugins/Daily Notes/2023-11-20.md",
    "Plugins/Daily Notes/2023-11-12.md",
    "Plugins/Daily Notes/2023-11-11.md",
    "Plugins/Daily Notes/2023-11-09.md",
    "Plugins/Daily Notes/2023-11-08.md",
    "Plugins/Daily Notes/2023-10-02.md",
    "Plugins/Daily Notes/2023-09-07.md",
    "Plugins/Daily Notes/2023-08-29.md",
    "Plugins/Excalidraw/Scripts/Downloaded/Mindmap format.svg",
    "Plugins/Excalidraw/Drawing 2023-07-12 17.54.08.excalidraw.md",
    "Plugins/Excalidraw/Danmaku Deconstruction.md",
    "Plugins/Excalidraw/Drawing 2023-09-26 12.35.45.excalidraw.md",
    "» Notes/✦ Papers/Resource",
    "Plugins/Canvas/Untitled.canvas",
    "Attachments/Pasted Image 20231123155426_934.png",
    "Plugins/Canvas/DFA.canvas",
    "Attachments/Pasted Image 20231110190127_936.png",
    "Plugins/Excalidraw/Scripts/Downloaded",
    "Plugins/Excalidraw/Scripts",
    "Attachments/Composition of the Universe.png",
    "Attachments/Pasted image 20231108203658.png",
    "Attachments/Pasted Image 20231108024832_292.png",
    "Attachments/Pasted image 20231106205002.png",
    "Attachments/Pasted image 20231106182758.png",
    "Attachments/Pasted image 20231106182323.png",
    "Attachments/Pasted image 20231024142949.png",
    "» Notes/Atomic",
    "» Notes/WIP",
    "Plugins/Canvas/Internet of Things.canvas",
    "Plugins/Canvas/Untitled 1.canvas",
    "Plugins/Canvas/OpenSystemsInterconnectionModel.canvas",
    "Plugins/Canvas/Notes.canvas",
    "Plugins/Canvas/DataCommunicationsAndNetworking.canvas",
    "Plugins/Canvas/Papers.canvas",
    "DataCommunicationsAndNetworking.canvas",
    "Plugins/Canvas/Machine Learning.canvas",
    "Plugins/Citations/references.bib",
    "Plugins/Citations",
    "» Notes/✦ Papers",
    "Notes/Untitled 1"
  ]
}