{
  "main": {
    "id": "cddc458a52dfc4c2",
    "type": "split",
    "children": [
      {
        "id": "7e6b492b79c0e433",
        "type": "tabs",
        "children": [
          {
            "id": "0d1b934a1fbd1e03",
            "type": "leaf",
            "state": {
              "type": "excalidraw",
              "state": {
                "file": "Plugins/Excalidraw/Untitled.md"
              }
            }
          },
          {
            "id": "c964bb393386aad7",
            "type": "leaf",
            "state": {
              "type": "markdown",
              "state": {
                "file": "Notes/temporary/Untitled.md",
                "mode": "source",
                "backlinks": true,
                "source": false
              }
            }
          }
        ],
        "currentTab": 1
      }
    ],
    "direction": "vertical"
  },
  "left": {
    "id": "a9db8479e8229784",
    "type": "split",
    "children": [
      {
        "id": "df71673bef8e97da",
        "type": "tabs",
        "children": [
          {
            "id": "cef6f232d564ca5a",
            "type": "leaf",
            "state": {
              "type": "file-explorer",
              "state": {
                "sortOrder": "alphabetical"
              }
            }
          },
          {
            "id": "341442d45d6b5e71",
            "type": "leaf",
            "state": {
              "type": "search",
              "state": {
                "query": "",
                "matchingCase": true,
                "explainSearch": false,
                "collapseAll": true,
                "extraContext": false,
                "sortOrder": "alphabetical"
              }
            }
          },
          {
            "id": "1bc11ef43887bc23",
            "type": "leaf",
            "state": {
              "type": "starred",
              "state": {}
            }
          },
          {
            "id": "3cdc0fa36b8d9777",
            "type": "leaf",
            "state": {
              "type": "bookmarks",
              "state": {}
            }
          },
          {
            "id": "d5e1e2be15a68b5c",
            "type": "leaf",
            "state": {
              "type": "file-tree-view",
              "state": {}
            }
          }
        ]
      }
    ],
    "direction": "horizontal",
    "width": 407.51103591918945
  },
  "right": {
    "id": "68e330dec2c08a37",
    "type": "split",
    "children": [
      {
        "id": "add047b1118d202a",
        "type": "tabs",
        "children": [
          {
            "id": "17eb92a6239b54df",
            "type": "leaf",
            "state": {
              "type": "backlink",
              "state": {
                "file": "Notes/temporary/Untitled.md",
                "collapseAll": false,
                "extraContext": false,
                "sortOrder": "alphabetical",
                "showSearch": false,
                "searchQuery": "",
                "backlinkCollapsed": false,
                "unlinkedCollapsed": false
              }
            }
          },
          {
            "id": "233dbe7a27ca4243",
            "type": "leaf",
            "state": {
              "type": "outgoing-link",
              "state": {
                "file": "Notes/temporary/Untitled.md",
                "linksCollapsed": false,
                "unlinkedCollapsed": false
              }
            }
          },
          {
            "id": "0c87cba199260fb0",
            "type": "leaf",
            "state": {
              "type": "advanced-tables-toolbar",
              "state": {}
            }
          },
          {
            "id": "21a4c9d080ba0b6d",
            "type": "leaf",
            "state": {
              "type": "tag",
              "state": {
                "sortOrder": "frequency",
                "useHierarchy": true
              }
            }
          },
          {
            "id": "9425de3f6185bf10",
            "type": "leaf",
            "state": {
              "type": "outline",
              "state": {
                "file": "Notes/temporary/Untitled.md"
              }
            }
          },
          {
            "id": "f8655c264c18d2d1",
            "type": "leaf",
            "state": {
              "type": "calendar",
              "state": {}
            }
          },
          {
            "id": "b351daec9efe29d0",
            "type": "leaf",
            "state": {
              "type": "FANTASY_CALENDAR",
              "state": {}
            }
          },
          {
            "id": "135277ee9e447b16",
            "type": "leaf",
            "state": {
              "type": "all-properties",
              "state": {
                "sortOrder": "frequency"
              }
            }
          }
        ],
        "currentTab": 2
      }
    ],
    "direction": "horizontal",
    "width": 300,
    "collapsed": true
  },
  "left-ribbon": {
    "hiddenItems": {
      "switcher:Open quick switcher": false,
      "graph:Open graph view": false,
      "canvas:Create new canvas": false,
      "daily-notes:Open today's daily note": false,
      "templates:Insert template": false,
      "command-palette:Open command palette": false,
      "obsidian-excalidraw-plugin:Create new drawing": false,
      "notion-like-tables:Create Notion-Like table": false,
      "table-editor-obsidian:Advanced Tables Toolbar": false,
      "file-tree-alternative:File Tree Alternative Plugin": false,
      "workspaces:Manage workspace layouts": false,
      "fantasy-calendar:Open Large Fantasy Calendar": false,
      "templater-obsidian:Templater": false
    }
  },
  "active": "c964bb393386aad7",
  "lastOpenFiles": [
    "Plugins/Excalidraw/Untitled.md",
    "Notes/temporary/Untitled.md",
    "Notes/SineWave.md",
    "Plugins/Daily Notes/2023-10-02.md",
    "Notes/temporary/HackThisSite - Basic Level 6.md",
    "Notes/temporary/old/CMSC 194.1 Task 1 Annotated Bibliography (BRIGS).md",
    "Attachments/Pasted image 20230926125012.png",
    "Notes/temporary/old",
    "Attachments/Pasted image 20230918043437.png",
    "Attachments/Pasted image 20230918041821.png",
    "Attachments/Pasted image 20230918030707.png",
    "Attachments/Pasted image 20230918025318.png",
    "Attachments/Pasted Image 20230913053822_217.png",
    "_OLD/ATTACHMENT_FOLDER/image3 1.png",
    "_OLD/ATTACHMENT_FOLDER/image2.png",
    "_OLD/ATTACHMENT_FOLDER/3.png",
    "_OLD/ATTACHMENT_FOLDER/image4.png",
    "_OLD/unorganized fuck/DEFINITIONS.md",
    "_OLD/unorganized fuck/2022-2023/REFERENCES.md",
    "_OLD/unorganized fuck/2022-2023/CMSC 194.1/Workshop 1/Lecture 1 - Annotated Bibliography.md",
    "_OLD/unorganized fuck/2022-2023/CMSC 192/Week 2 (19-23 September 2022)/Introduction to Computer Ethics.md",
    "_OLD/unorganized fuck/2022-2023/CMSC 142/Week 1/MP1 Primer.md",
    "_OLD/unorganized fuck/2022-2023/CMSC 128/Week 2 - Software Process Models/Software Process Models.md",
    "_OLD/unorganized fuck/2022-2023/CMSC 128/Week 2 - Software Process Models/Laboratory Exercise 2.md",
    "_OLD/unorganized fuck/2022-2023/CMSC 128/Week 1 - Introduction to Software Engineering/Software Horror Stories.md",
    "_OLD/unorganized fuck/2022-2023/CMSC 128/Week 1 - Introduction to Software Engineering/Software Engineering and Processes.md",
    "_OLD/unorganized fuck/2022-2023/CMSC 128/Week 1 - Introduction to Software Engineering/Software.md",
    "_OLD/unorganized fuck/2022-2023/CMSC 124/INFO_DUMP.md",
    "_OLD/unorganized fuck/2022-2023/CMSC 124/Week 3-4/Syntax and Semantics.md",
    "_OLD/unorganized fuck/2022-2023/CMSC 124/Week 3-4/Backus-Naur Form.md",
    "_OLD/unorganized fuck/2022-2023/CMSC 124/Week 2/MP1 Source Codes.md",
    "_OLD/unorganized fuck/2022-2023/CMSC 124/Week 2/Background Concepts.md",
    "_OLD/unorganized fuck/2022-2023/CMSC 110/Technical Writing Essentials.md",
    "_OLD/Notes/020 Studies/Static Interconnection Networks.md",
    "_OLD/Notes/020 Studies/Utilitarianism.md",
    "_OLD/Notes/020 Studies/Spooling.md",
    "_OLD/Notes/020 Studies/Single Buffering.md",
    "_OLD/Notes/020 Studies/chapter14 characters.canvas",
    "Plugins/Notion/window manager checklist.table",
    "Plugins/Canvas/Untitled 1.canvas",
    "Plugins/Canvas/Untitled.canvas",
    "Plugins/Canvas/Machine Learning.canvas",
    "Plugins/Canvas/DFA.canvas",
    "_OLD2/__class/090 extras",
    "_OLD2/__class/020 linux",
    "_OLD2/__class/010 learning",
    "_OLD2/__orphans",
    "_OLD2/__index",
    "_OLD2/__class",
    "_OLD2",
    "Notes/temporary",
    "Canvas/Untitled.canvas",
    "Untitled 1.canvas",
    "Image Analysis.canvas"
  ]
}